eveparse/__init__.py
eveparse/constants.py
eveparse/converters.py
eveparse/errors.py
eveparse/validators.py
eveparse/data/invTypes.json
eveparse/parsers/__init__.py
eveparse/parsers/base.py
eveparse/parsers/contract.py
eveparse/parsers/contractnodetails.py
eveparse/parsers/nameonly.py
eveparse/parsers/namespacequantity.py
eveparse/parsers/namespacexquantity.py
eveparse/parsers/nametabquantity.py
eveparse/parsers/quantityspacename.py
eveparse/parsers/quantityspacexspacename.py
eveparse/parsers/quantityxspacename.py
eveparse/parsers/shipfitname.py
eveparse-0.0.1.dist-info/METADATA
eveparse-0.0.1.dist-info/WHEEL
eveparse-0.0.1.dist-info/licenses/LICENSE
eveparse-0.0.1.dist-info/RECORD
