Metadata-Version: 2.1
Name: eveparse
Version: 0.0.1
Summary: Parser for Eve Online - extract item name and quantity from a string
Project-URL: Homepage, https://github.com/harrelchris/eveparse
Project-URL: Bug Tracker, https://github.com/harrelchris/eveparse/issues
Author-email: Chris Harrel <24297899+harrelchris@users.noreply.github.com>
License: Copyright 2023 Chris Harrel
License-File: LICENSE
Classifier: License :: OSI Approved :: MIT License
Classifier: Operating System :: OS Independent
Classifier: Programming Language :: Python :: 3
Requires-Python: >=3.7
